gitlo.py
gitlo-1.0.1.dist-info/METADATA
gitlo-1.0.1.dist-info/RECORD
gitlo-1.0.1.dist-info/WHEEL
gitlo-1.0.1.dist-info/entry_points.txt
gitlo-1.0.1.dist-info/top_level.txt
