Metadata-Version: 2.1
Name: gitlo
Version: 1.0.1
Summary: A Command Line Interface for accessing Github api.
Home-page: https://github.com/SiddharthShringi/Gitpy
Author: Siddharth Shringi
Author-email: siddharthshrigi@gmail.com
License: UNKNOWN
Platform: UNKNOWN
Classifier: Programming Language :: Python :: 3
Classifier: License :: OSI Approved :: MIT License
Requires-Dist: Click
Requires-Dist: Requests
